{
  "total": 1,
  "offset": 0,
  "limit": 1,
  "data": [
    {
      "GetCredential": {
        "className": "getCredentialContainer",
        "templateId": "671938c0a355389273dc7a8f",
        "stageTemplateId": "667b0b6a6547797329d24f0d",
        "productName": "Adobe Experience Platform",
        "components": {
          "SignIn": {
            "title": "Get credentials",
            "paragraph": "After signing in, you can create credentials that can be used to call the Platform APIs.",
            "buttonText": "Sign in"
          },
          "Form": {
            "title": "Get credentials",
            "paragraph": "Create credentials that you can use to call the Platform APIs.",
            "className": "formClass",
            "components": {
              "CredentialName": {
                "label": "Credential name",
                "description": "The credential name must be unique, use alphanumeric characters, and between 6 and 45 characters long. A project will be automatically created with the same name in Adobe Developer Console.",
                "range": "45"
              },
              "Products": {
                "label": "Included products and services",
                "items": [
                  {
                    "Product": {
                      "label": "Adobe Experience Platform",
                      "icon": "https://raw.githubusercontent.com/AdobeDocs/experience-platform-apis/main/src/pages/credentials/images/platform.png"
                    }
                  }
                ]
              },
              "AdobeDeveloperConsole": {
                "label": "By checking this box, you agree to",
                "linkText": "Adobe Developer Terms of Use",
                "href": "https://wwwimages2.adobe.com/content/dam/cc/en/legal/servicetou/Adobe-Developer-Additional-Terms_en-US_20230822.pdf"
              },
              "Side": {
                "content": {
                  "style": {
                    "display": "flex",
                    "gap": "16px",
                    "flexDirection": "column"
                  },
                  "elements": [
                    {
                      "type": "h3",
                      "className": "spectrum-Heading spectrum-Heading--sizeS side-header",
                      "text": "OAuth server-to-server credential"
                    },
                    {
                      "type": "p",
                      "className": "spectrum-Body spectrum-Body--sizeM",
                      "text": "This credential allows you to use industry standard OAuth2.0 libraries to generate access tokens using the OAuth 2.0 client credentials grant type."
                    },
                    {
                      "type": "h3",
                      "className": "spectrum-Heading spectrum-Heading--sizeS side-header",
                      "text": "Learn more"
                    },
                    {
                      "type": "a",
                      "className": "side-documentation",
                      "style": {
                        "color": "#0265DC"
                      },
                      "href": "https://experienceleague.adobe.com/en/docs/experience-platform/landing/platform-apis/api-authentication",
                      "text": "Authentication documentation"
                    },
                    {
                      "type": "a",
                      "className": "side-documentation",
                      "style": {
                        "color": "#0265DC"
                      },
                      "href": "https://experienceleague.adobe.com/en/docs/experience-platform/landing/platform-apis/api-guide",
                      "text": "Adobe Experience Platform API documentation"
                    },
                    {
                      "type": "a",
                      "className": "side-documentation",
                      "style": {
                        "color": "#0265DC"
                      },
                      "href": "https://experienceleague.adobe.com/en/docs/experience-platform",
                      "text": "Adobe Experience Platform documentation"
                    }
                  ]
                }
              }
            }
          },
          "Card": {
            "title": "Your credential is ready to use",
            "developerConsoleManage": "Manage on Developer Console",
            "className": "card_developer_console",
            "devConsoleDirection": "https://developer.adobe.com/console",
            "isCollapsable": "true",
            "components": {
              "Side": {
                "content": {
                  "style": {
                    "display": "flex",
                    "gap": "16px",
                    "flexDirection": "column"
                  },
                  "elements": [
                    {
                      "type": "h3",
                      "className": "spectrum-Heading spectrum-Heading--sizeS side-header",
                      "text": "OAuth server-to-server credential"
                    },
                    {
                      "type": "p",
                      "className": "spectrum-Body spectrum-Body--sizeM",
                      "text": "This credential allows you to use industry standard OAuth2.0 libraries to generate access tokens using the OAuth 2.0 client credentials grant type."
                    },
                    {
                      "type": "h3",
                      "className": "spectrum-Heading spectrum-Heading--sizeS side-header",
                      "text": "Learn more"
                    },
                    {
                      "type": "a",
                      "className": "side-documentation",
                      "style": {
                        "color": "#0265DC"
                      },
                      "href": "https://experienceleague.adobe.com/en/docs/experience-platform/landing/platform-apis/api-authentication",
                      "text": "Authentication documentation"
                    },
                    {
                      "type": "a",
                      "className": "side-documentation",
                      "style": {
                        "color": "#0265DC"
                      },
                      "href": "https://experienceleague.adobe.com/en/docs/experience-platform/landing/platform-apis/api-guide",
                      "text": "Adobe Experience Platform API documentation"
                    },
                    {
                      "type": "a",
                      "className": "side-documentation",
                      "style": {
                        "color": "#0265DC"
                      },
                      "href": "https://experienceleague.adobe.com/en/docs/experience-platform",
                      "text": "Adobe Experience Platform documentation"
                    }
                  ]
                }
              },
              "Products": {
                "label": "Included products and services",
                "items": [
                  {
                    "Product": {
                      "label": "Adobe Experience Platform",
                      "icon": "https://raw.githubusercontent.com/AdobeDocs/experience-platform-apis/main/src/pages/credentials/images/platform.png"
                    }
                  }
                ]
              },
              "ProjectsDropdown": {
                "label": "Projects",
                "subHeading": "Only your projects that contain credentials are shown"
              },
              "ManageDeveloperConsole": {
                "label": "Manage all your projects and credentials on Adobe Developer Console",
                "direction": "https://developer.adobe.com/console"
              },
              "DevConsoleLink": {
                "heading": "Developer Console Project"
              },
              "AccessToken": {
                "helpText": "",
                "buttonLabel": "Generate and copy token",
                "heading": "Access token<br/><br/> <span style=\"font-weight:normal\"><small>After copying the access token, you must prepend the token with <code>Bearer</code> to use it with API calls.</small></span>"
              },
              "CredentialDetails": {
                "heading": "Credential details<br/><br/> <span style=\"font-weight:normal\"><small>You can use the following credential details to try out the Adobe Experience Platform APIs below.<ul><li>Client ID: Your public identifier for accessing the APIs. This acts as an API key when used with the Platform APIs, and corresponds with the <code>x-api-key</code> header.</li><li>Organization ID: The ID of the organization you're using with the Platform APIs. This corresponds with the <code>x-gw-ims-org-id</code> header.</li></ul></small></span>",
                "orderBy": "ClientId,ImsOrgID",
                "components": {
                  "ClientId": {
                    "heading": "Client ID (x-api-key)"
                  },
                  "ImsOrgID": {
                    "heading": "Organization ID"
                  },
                  "Scopes": {
                    "heading": "Scopes",
                    "scope": "openid,session,AdobeID,read_organizations,additional_info.projectedProductContext"
                  }
                }
              }
            }
          },
          "Return": {
            "title": "Previously created projects",
            "paragraph": "Select a project and access your existing credentials for Adobe Experience Platform.",
            "className": "card_developer_console",
            "isCollapsable": "true",
            "components": {
              "Side": {
                "components": {
                  "Custom": {
                    "content": {
                      "style": {
                        "display": "flex",
                        "gap": "30px",
                        "flexDirection": "column",
                        "width": "100%"
                      },
                      "elements": [
                        {
                          "type": "h3",
                          "className": "spectrum-Heading spectrum-Heading--sizeM",
                          "text": "Welcome back"
                        },
                        {
                          "type": "p",
                          "className": "spectrum-Body spectrum-Body--sizeM",
                          "text": "You can either re-use an existing credential or create a new credential."
                        }
                      ]
                    }
                  },
                  "NewCredential": {
                    "heading": "Need another credential?",
                    "buttonLabel": "Create new credential"
                  }
                }
              },
              "CredentialDetails": {
                "heading": "Credential details<br/><br/> <span style=\"font-weight:normal\"><small>You can use the following credential details to try out the Adobe Experience Platform APIs below.<ul><li>Client ID: Your public identifier for accessing the APIs. This acts as an API key when used with the Platform APIs, and corresponds with the <code>x-api-key</code> header.</li><li>Organization ID: The ID of the organization you're using with the Platform APIs. This corresponds with the <code>x-gw-ims-org-id</code> header.</li></ul></small></span>",
                "orderBy": "ClientId,ImsOrgID",
                "components": {
                  "ClientId": {
                    "heading": "Client ID (x-api-key)"
                  },
                  "ImsOrgID": {
                    "heading": "Organization ID"
                  },
                  "Scopes": {
                    "heading": "Scopes",
                    "scope": "openid,session,AdobeID,read_organizations,additional_info.projectedProductContext"
                  }
                }
              },
              "ProjectsDropdown": {
                "label": "Projects",
                "subHeading": "Only your projects that contain credentials are shown"
              },
              "ManageDeveloperConsole": {
                "label": "Manage all your projects and credentials on Adobe Developer Console",
                "direction": "https://developer.adobe.com/console/projects"
              },
              "AccessToken": {
                "helpText": "",
                "buttonLabel": "Generate and copy token",
                "heading": "Access token<br/><br/> <span style=\"font-weight:normal\"><small>After copying the access token, you must prepend the token with <code>Bearer</code> to use it with API calls.</small></span>"
              },
              "DevConsoleLink": {
                "heading": "Developer Console project"
              },
              "Products": {
                "label": "Included products and services",
                "items": [
                  {
                    "Product": {
                      "label": "Adobe Experience Platform",
                      "icon": "https://raw.githubusercontent.com/AdobeDocs/experience-platform-apis/main/src/pages/credentials/images/platform.png"
                    }
                  }
                ]
              }
            }
          },
          "RequestAccess": {
            "title": "Get credentials",
            "paragraph": "Create unique credentials that you will use to call multiple APIs from your application.",
            "components": {
              "EdgeCase": {
                "components": {
                  "NoProduct": {
                    "title": "Your organization does not have access to Adobe Experience Platform."
                  },
                  "Type1User": {
                    "title": "You do not have access to Adobe Experience Platform. Please use another organization and try again."
                  },
                  "NotMember": {
                    "title": "You do not have access to Adobe Experience Platform. Please use another organization and try again."
                  }
                }
              },
              "RestrictedAccess": {
                "title": "Restricted Access",
                "buttonLabel": "Request access",
                "components": {
                  "Products": {
                    "label": "Included products and services",
                    "items": [
                      {
                        "Product": {
                          "label": "Adobe Experience Platform",
                          "icon": "https://raw.githubusercontent.com/AdobeDocs/experience-platform-apis/main/src/pages/credentials/images/platform.png"
                        }
                      }
                    ]
                  }
                }
              },
              "RequestAccessSide": {
                "content": {
                  "style": {
                    "display": "flex",
                    "gap": "16px",
                    "flexDirection": "column"
                  },
                  "elements": [
                    {
                      "type": "h3",
                      "className": "spectrum-Heading spectrum-Heading--sizeS side-header",
                      "text": "OAuth server-to-server credential"
                    },
                    {
                      "type": "p",
                      "className": "spectrum-Body spectrum-Body--sizeM",
                      "text": "This credential allows you to use industry standard OAuth2.0 libraries to generate access tokens using the OAuth 2.0 client credentials grant type."
                    },
                    {
                      "type": "h3",
                      "className": "spectrum-Heading spectrum-Heading--sizeS side-header",
                      "text": "Learn more"
                    },
                    {
                      "type": "a",
                      "className": "side-documentation",
                      "style": {
                        "color": "#0265DC"
                      },
                      "href": "https://experienceleague.adobe.com/en/docs/experience-platform/landing/platform-apis/api-authentication",
                      "text": "Authentication documentation"
                    },
                    {
                      "type": "a",
                      "className": "side-documentation",
                      "style": {
                        "color": "#0265DC"
                      },
                      "href": "https://experienceleague.adobe.com/en/docs/experience-platform/landing/platform-apis/api-guide",
                      "text": "Adobe Experience Platform API documentation"
                    },
                    {
                      "type": "a",
                      "className": "side-documentation",
                      "style": {
                        "color": "#0265DC"
                      },
                      "href": "https://experienceleague.adobe.com/en/docs/experience-platform",
                      "text": "Adobe Experience Platform documentation"
                    }
                  ]
                }
              }
            }
          }
        }
      }
    }
  ],
  ":type": "sheet"
}
